[
  { "name": "Niczzy", "key": "uejogor5r4he9ziyebybftaimk6pmc" },
  { "name": "Plazo", "key": "u6hfr9kja2259nnnggcbmej479eb2q" },
  { "name": "Xpert", "key": "utrn3xof5k6ryajcwiqaoi181xn7as" },
  { "name": "Martin", "key": "u51qtapfo3oji82ypixto16d6h9yhp" },
  { "name": "Clipped", "key": "u9mio58xxfj79yxb7hazuay4nbwdg8" },
  { "name": "Owari", "key": "udcvanbbwzhk3b1jpq1nezs1ftnygj" },
  { "name": "Twin", "key": "uutdsu7ca913ims78x3i8ebibjc6oi" },
  { "name": "Rolf", "key": "uzj9bwb77u3rah33sudsuaptxg6wwd" },
  { "name": "Splashy", "key": "u6x2fc1fsuz1u2d5gog96ythtczhxh" },
  { "name": "Rickey", "key": "udbx9hhmtvavr3bf7vs4dyxrxvqud6" },
  { "name": "Dimi", "key": "ufwvs6w4o3tv23zg5d37o8vdktdazs" },
  { "name": "Anouar", "key": "ukiba7j5q6kvnzngu6uowkbwkmptba" },
  { "name": "Bogdanoff", "key": "ufjdq98emf5u3pzmb4gb6jhqgmdwkt" },
  { "name": "Diimax", "key": "u8p6w9x8n3b62bcxguit7jc5i3uamy" },
  { "name": "Ducky", "key": "uv4ex3soey4x8s7eaqten7wjef26os" },
  { "name": "Runetoshi", "key": "ujd21ayatigfvwcng2pby2a8xjrm59" },
  { "name": "Flasherman", "key": "uujjedszsqi2zs5msmyq3xr3b5bumf" }
]


